{
  "0": {
    "full_model": {
      "best_combinational": {
        "accuracy": 0.821667,
        "indices": {
          "321": [
            8,
            5
          ]
        },
        "loss": -247.727
      },
      "final_elo_scores": [
        -21.1067,
        -401.429,
        213.298,
        -81.4539,
        -180.857,
        -252.849,
        125.634,
        39.2376,
        367.428,
        192.074
      ],
      "k_c": 495.34,
      "k_g": 37.2757
    },
    "optimized_elo": {
      "accuracy": 0.801667,
      "final_elo_scores": [
        -59.8332,
        -463.975,
        242.058,
        -72.4442,
        -184.995,
        -268.182,
        144.801,
        46.6579,
        407.278,
        208.611
      ],
      "k_g": 72.5562,
      "loss": -258.57
    }
  },
  "1": {
    "full_model": {
      "best_combinational": {
        "accuracy": 0.821667,
        "indices": {
          "165": [
            8,
            9
          ],
          "381": [
            9,
            0
          ]
        },
        "loss": -227.037
      },
      "final_elo_scores": [
        -343.284,
        -303.435,
        -249.06,
        277.18,
        225.102,
        -23.8182,
        19.6179,
        75.9365,
        338.308,
        -16.5416
      ],
      "k_c": 511.961,
      "k_g": 41.3911
    },
    "optimized_elo": {
      "accuracy": 0.798333,
      "final_elo_scores": [
        -323.233,
        -280.287,
        -269.471,
        326.889,
        230.956,
        -41.2717,
        56.5724,
        32.8147,
        344.87,
        -77.832
      ],
      "k_g": 72.1143,
      "loss": -257.849
    }
  },
  "10": {
    "full_model": {
      "best_combinational": {
        "accuracy": 0.785,
        "indices": {
          "264": [
            7,
            6
          ],
          "377": [
            5,
            2
          ]
        },
        "loss": -252.33
      },
      "final_elo_scores": [
        -205.354,
        266.38,
        -418.807,
        95.967,
        206.585,
        493.087,
        -505.185,
        217.672,
        -119.566,
        -30.7134
      ],
      "k_c": 610.666,
      "k_g": 43.0282
    },
    "optimized_elo": {
      "accuracy": 0.755,
      "final_elo_scores": [
        -240.825,
        312.435,
        -268.647,
        85.2845,
        134.203,
        376.764,
        -385.668,
        155.332,
        -148.078,
        -20.7532
      ],
      "k_g": 69.9786,
      "loss": -286.882
    }
  },
  "11": {
    "full_model": {
      "best_combinational": {
        "accuracy": 0.798333,
        "indices": {
          "221": [
            7,
            5
          ]
        },
        "loss": -251.067
      },
      "final_elo_scores": [
        131.151,
        -82.9839,
        -147.736,
        -275.524,
        56.171,
        -161.2,
        332.353,
        265.156,
        80.4294,
        -197.854
      ],
      "k_c": 320.854,
      "k_g": 37.4726
    },
    "optimized_elo": {
      "accuracy": 0.791667,
      "final_elo_scores": [
        154.373,
        -89.3868,
        -169.284,
        -302.218,
        46.9914,
        -188.237,
        393.675,
        294.509,
        106.851,
        -247.277
      ],
      "k_g": 60.7794,
      "loss": -261.667
    }
  },
  "12": {
    "full_model": {
      "best_combinational": {
        "accuracy": 0.776667,
        "indices": {
          "125": [
            3,
            0
          ],
          "216": [
            2,
            1
          ]
        },
        "loss": -268.965
      },
      "final_elo_scores": [
        -411.36,
        -110.242,
        189.282,
        297.216,
        -68.8713,
        -84.1329,
        166.205,
        -175.98,
        163.251,
        34.6333
      ],
      "k_c": 411.824,
      "k_g": 31.1867
    },
    "optimized_elo": {
      "accuracy": 0.766667,
      "final_elo_scores": [
        -434.424,
        -54.0086,
        160.961,
        325.506,
        -102.891,
        -116.277,
        229.059,
        -230.265,
        209.882,
        12.4507
      ],
      "k_g": 59.3299,
      "loss": -286.154
    }
  },
  "13": {
    "full_model": {
      "best_combinational": {
        "accuracy": 0.833333,
        "indices": {
          "158": [
            7,
            4
          ]
        },
        "loss": -223.284
      },
      "final_elo_scores": [
        -212.273,
        136.752,
        -298.973,
        21.3945,
        -282.337,
        -61.4136,
        12.9366,
        416.263,
        211.938,
        55.7175
      ],
      "k_c": 504.065,
      "k_g": 33.748
    },
    "optimized_elo": {
      "accuracy": 0.811667,
      "final_elo_scores": [
        -207.673,
        173.748,
        -328.838,
        11.824,
        -284.057,
        -82.1126,
        50.9432,
        433.07,
        185.624,
        47.4768
      ],
      "k_g": 57.0849,
      "loss": -242.363
    }
  },
  "14": {
    "full_model": {
      "best_combinational": {
        "accuracy": 0.853333,
        "indices": {
          "113": [
            7,
            9
          ],
          "114": [
            5,
            0
          ],
          "308": [
            0,
            7
          ]
        },
        "loss": -213.607
      },
      "final_elo_scores": [
        266.307,
        324.462,
        125.905,
        -40.4363,
        -197.455,
        109.332,
        117.716,
        -198.29,
        -225.176,
        -282.284
      ],
      "k_c": 520.589,
      "k_g": 34.1152
    },
    "optimized_elo": {
      "accuracy": 0.825,
      "final_elo_scores": [
        312.162,
        359.977,
        111.358,
        -40.882,
        -224.219,
        72.7929,
        171.906,
        -200.662,
        -266.565,
        -295.843
      ],
      "k_g": 66.6957,
      "loss": -247.998
    }
  },
  "15": {
    "full_model": {
      "best_combinational": {
        "accuracy": 0.853333,
        "indices": {
          "142": [
            6,
            0
          ],
          "274": [
            4,
            6
          ]
        },
        "loss": -204.828
      },
      "final_elo_scores": [
        -483.413,
        -169.564,
        148.695,
        -313.456,
        -34.5934,
        77.1598,
        -93.5209,
        468.235,
        83.1416,
        317.228
      ],
      "k_c": 569.921,
      "k_g": 61.176
    },
    "optimized_elo": {
      "accuracy": 0.835,
      "final_elo_scores": [
        -460.127,
        -188.524,
        135.156,
        -329.119,
        -44.227,
        63.0479,
        -103.045,
        478.653,
        116.316,
        331.781
      ],
      "k_g": 83.4809,
      "loss": -236.631
    }
  },
  "16": {
    "full_model": {
      "best_combinational": {
        "accuracy": 0.795,
        "indices": {
          "140": [
            9,
            1
          ],
          "395": [
            0,
            4
          ]
        },
        "loss": -246.152
      },
      "final_elo_scores": [
        232.728,
        -432.945,
        16.2888,
        -30.9716,
        -273.906,
        116.534,
        -180.631,
        -36.3324,
        179.546,
        409.581
      ],
      "k_c": 586.075,
      "k_g": 21.6141
    },
    "optimized_elo": {
      "accuracy": 0.768333,
      "final_elo_scores": [
        212.644,
        -357.83,
        3.92962,
        -40.9369,
        -249.002,
        149.292,
        -205.956,
        -33.599,
        109.462,
        411.939
      ],
      "k_g": 52.078,
      "loss": -267.746
    }
  },
  "17": {
    "full_model": {
      "best_combinational": {
        "accuracy": 0.84,
        "indices": {
          "15": [
            8,
            6
          ],
          "105": [
            6,
            8
          ],
          "248": [
            7,
            0
          ],
          "358": [
            8,
            2
          ],
          "511": [
            3,
            5
          ]
        },
        "loss": -233.048
      },
      "final_elo_scores": [
        -272.9,
        40.2385,
        -300.619,
        233.759,
        55.9436,
        -376.208,
        166.02,
        331.136,
        264.536,
        -141.899
      ],
      "k_c": 529.775,
      "k_g": 26.6379
    },
    "optimized_elo": {
      "accuracy": 0.798333,
      "final_elo_scores": [
        -249.276,
        41.7715,
        -278.192,
        138.845,
        -11.8759,
        -304.386,
        146.225,
        358.008,
        313.494,
        -154.596
      ],
      "k_g": 76.2338,
      "loss": -274.028
    }
  },
  "18": {
    "full_model": {
      "best_combinational": {
        "accuracy": 0.826667,
        "indices": {
          "193": [
            9,
            1
          ],
          "377": [
            5,
            9
          ]
        },
        "loss": -240.826
      },
      "final_elo_scores": [
        79.1319,
        49.6274,
        -151.08,
        317.693,
        -98.7688,
        166.809,
        271.726,
        -148.709,
        -221.923,
        -264.59
      ],
      "k_c": 558.274,
      "k_g": 46.7597
    },
    "optimized_elo": {
      "accuracy": 0.796667,
      "final_elo_scores": [
        120.116,
        55.3932,
        -127.742,
        371.744,
        -157.26,
        161.282,
        304.408,
        -125.125,
        -270.738,
        -332.106
      ],
      "k_g": 80.211,
      "loss": -281.832
    }
  },
  "19": {
    "full_model": {
      "best_combinational": {
        "accuracy": 0.765,
        "indices": {
          "205": [
            2,
            8
          ],
          "386": [
            8,
            3
          ]
        },
        "loss": -293.132
      },
      "final_elo_scores": [
        -97.9817,
        -122.916,
        164.05,
        -326.172,
        146.423,
        -184.505,
        236.889,
        -8.69258,
        191.664,
        1.18394
      ],
      "k_c": 397.801,
      "k_g": 29.6779
    },
    "optimized_elo": {
      "accuracy": 0.725,
      "final_elo_scores": [
        -132.503,
        -136.114,
        198.015,
        -310.355,
        130.963,
        -191.735,
        263.389,
        -45.2859,
        204.041,
        19.584
      ],
      "k_g": 52.1374,
      "loss": -322.75
    }
  },
  "2": {
    "full_model": {
      "best_combinational": {
        "accuracy": 0.848333,
        "indices": {
          "79": [
            2,
            5
          ],
          "211": [
            4,
            9
          ]
        },
        "loss": -211.72
      },
      "final_elo_scores": [
        22.94,
        166.707,
        230.651,
        -42.0569,
        458.311,
        -298.812,
        -305.412,
        45.2101,
        112.898,
        -390.491
      ],
      "k_c": 650.855,
      "k_g": 35.8529
    },
    "optimized_elo": {
      "accuracy": 0.826667,
      "final_elo_scores": [
        -25.0773,
        186.384,
        195.017,
        -57.0274,
        427.079,
        -288.789,
        -292.776,
        57.6893,
        108.147,
        -310.7
      ],
      "k_g": 58.4299,
      "loss": -236.379
    }
  },
  "20": {
    "full_model": {
      "best_combinational": {
        "accuracy": 0.818333,
        "indices": {
          "170": [
            4,
            1
          ],
          "351": [
            7,
            4
          ]
        },
        "loss": -242.859
      },
      "final_elo_scores": [
        229.716,
        -397.187,
        -136.368,
        -178.675,
        -21.6377,
        218.159,
        -112.49,
        443.988,
        6.39476,
        -51.9373
      ],
      "k_c": 575.634,
      "k_g": 38.7653
    },
    "optimized_elo": {
      "accuracy": 0.8,
      "final_elo_scores": [
        221.668,
        -427.866,
        -168.774,
        -174.004,
        3.84058,
        282.399,
        -91.5566,
        423.315,
        8.12131,
        -77.1822
      ],
      "k_g": 78.8499,
      "loss": -276.886
    }
  },
  "21": {
    "full_model": {
      "best_combinational": {
        "accuracy": 0.848333,
        "indices": {
          "152": [
            2,
            0
          ],
          "275": [
            0,
            2
          ]
        },
        "loss": -222.84
      },
      "final_elo_scores": [
        -226.413,
        289.224,
        -401.054,
        373.263,
        201.556,
        37.3003,
        -96.0255,
        -16.4226,
        80.5299,
        -241.949
      ],
      "k_c": 596.142,
      "k_g": 42.1103
    },
    "optimized_elo": {
      "accuracy": 0.803333,
      "final_elo_scores": [
        -260.421,
        316.445,
        -393.793,
        431.409,
        238.437,
        11.6477,
        -97.3781,
        -13.8906,
        73.2945,
        -305.807
      ],
      "k_g": 72.0262,
      "loss": -254.573
    }
  },
  "22": {
    "full_model": {
      "best_combinational": {
        "accuracy": 0.855,
        "indices": {
          "119": [
            0,
            1
          ],
          "354": [
            1,
            7
          ]
        },
        "loss": -222.898
      },
      "final_elo_scores": [
        332.572,
        231.888,
        -33.4545,
        -255.601,
        51.191,
        190.113,
        -116.481,
        -431.075,
        -152.625,
        183.438
      ],
      "k_c": 511.56,
      "k_g": 27.3483
    },
    "optimized_elo": {
      "accuracy": 0.813333,
      "final_elo_scores": [
        302.867,
        259.713,
        -88.7829,
        -287.234,
        63.7338,
        281.667,
        -111.26,
        -380.576,
        -201.911,
        161.734
      ],
      "k_g": 68.9963,
      "loss": -253.591
    }
  },
  "23": {
    "full_model": {
      "best_combinational": {
        "accuracy": 0.843333,
        "indices": {
          "65": [
            3,
            1
          ],
          "292": [
            1,
            3
          ]
        },
        "loss": -209.535
      },
      "final_elo_scores": [
        210.461,
        76.7912,
        -320.699,
        -242.149,
        27.845,
        249.123,
        -169.61,
        -244.557,
        364.024,
        48.7729
      ],
      "k_c": 520.201,
      "k_g": 35.9933
    },
    "optimized_elo": {
      "accuracy": 0.808333,
      "final_elo_scores": [
        239.841,
        35.6001,
        -373.876,
        -259.54,
        74.0386,
        257.702,
        -168.25,
        -293.59,
        424.494,
        63.5844
      ],
      "k_g": 71.2656,
      "loss": -239.458
    }
  },
  "24": {
    "full_model": {
      "best_combinational": {
        "accuracy": 0.835,
        "indices": {
          "94": [
            2,
            8
          ],
          "138": [
            3,
            7
          ],
          "359": [
            8,
            3
          ]
        },
        "loss": -225.835
      },
      "final_elo_scores": [
        -0.641322,
        -118.635,
        465.126,
        -138.664,
        -291.017,
        -219.932,
        146.55,
        -151.712,
        230.272,
        78.653
      ],
      "k_c": 517.314,
      "k_g": 34.4408
    },
    "optimized_elo": {
      "accuracy": 0.808333,
      "final_elo_scores": [
        47.6213,
        -156.538,
        479.17,
        -129.38,
        -327.412,
        -255.179,
        138.723,
        -138.594,
        245.39,
        96.1983
      ],
      "k_g": 68.0092,
      "loss": -255.594
    }
  },
  "25": {
    "full_model": {
      "best_combinational": {
        "accuracy": 0.796667,
        "indices": {
          "213": [
            9,
            2
          ],
          "350": [
            0,
            9
          ]
        },
        "loss": -276.081
      },
      "final_elo_scores": [
        47.5351,
        -142.855,
        -124.902,
        70.9421,
        -82.5266,
        89.0932,
        81.5696,
        86.6676,
        271.02,
        -296.682
      ],
      "k_c": 407.835,
      "k_g": 34.9007
    },
    "optimized_elo": {
      "accuracy": 0.765,
      "final_elo_scores": [
        47.0933,
        -229.759,
        -143.287,
        2.42953,
        -53.8002,
        169.024,
        100.178,
        79.0873,
        337.479,
        -308.568
      ],
      "k_g": 67.4864,
      "loss": -303.989
    }
  },
  "26": {
    "full_model": {
      "best_combinational": {
        "accuracy": 0.831667,
        "indices": {
          "163": [
            2,
            4
          ],
          "299": [
            1,
            6
          ],
          "349": [
            8,
            5
          ]
        },
        "loss": -226.469
      },
      "final_elo_scores": [
        299.097,
        89.1893,
        117.197,
        -82.3546,
        -265.578,
        -41.5199,
        -274.231,
        -161.556,
        278.105,
        41.6217
      ],
      "k_c": 330.907,
      "k_g": 4.31728e-136
    },
    "optimized_elo": {
      "accuracy": 0.811667,
      "final_elo_scores": [
        265.227,
        87.5738,
        11.1404,
        25.4917,
        -286.238,
        -69.041,
        -199.686,
        -213.539,
        290.386,
        88.6633
      ],
      "k_g": 40.6846,
      "loss": -251.931
    }
  },
  "27": {
    "full_model": {
      "best_combinational": {
        "accuracy": 0.86,
        "indices": {
          "233": [
            2,
            9
          ]
        },
        "loss": -210.029
      },
      "final_elo_scores": [
        316.434,
        2.29916,
        374.201,
        -63.0856,
        -286.486,
        111.485,
        -103.576,
        9.94174,
        91.7499,
        -452.811
      ],
      "k_c": 600.185,
      "k_g": 34.9454
    },
    "optimized_elo": {
      "accuracy": 0.845,
      "final_elo_scores": [
        345.492,
        -4.88897,
        422.352,
        -51.0751,
        -312.828,
        101.749,
        -193.957,
        13.5179,
        123.273,
        -443.483
      ],
      "k_g": 72.1639,
      "loss": -230.267
    }
  },
  "28": {
    "full_model": {
      "best_combinational": {
        "accuracy": 0.805,
        "indices": {
          "207": [
            8,
            0
          ],
          "302": [
            2,
            8
          ]
        },
        "loss": -261.98
      },
      "final_elo_scores": [
        -65.6643,
        300.629,
        230.153,
        47.1753,
        -207.723,
        -196.36,
        -24.7293,
        -164.96,
        -87.3019,
        168.723
      ],
      "k_c": 372.973,
      "k_g": 35.2183
    },
    "optimized_elo": {
      "accuracy": 0.778333,
      "final_elo_scores": [
        -62.3797,
        331.103,
        248.607,
        50.8696,
        -200.997,
        -244.281,
        -45.084,
        -198.147,
        -100.552,
        220.825
      ],
      "k_g": 58.3915,
      "loss": -284.865
    }
  },
  "29": {
    "full_model": {
      "best_combinational": {
        "accuracy": 0.806667,
        "indices": {
          "207": [
            9,
            2
          ],
          "249": [
            5,
            0
          ]
        },
        "loss": -251.516
      },
      "final_elo_scores": [
        -156.983,
        -17.1023,
        -336.967,
        17.5465,
        -227.387,
        257.007,
        -99.957,
        267.446,
        -36.5432,
        332.95
      ],
      "k_c": 445.911,
      "k_g": 39.7317
    },
    "optimized_elo": {
      "accuracy": 0.79,
      "final_elo_scores": [
        -154.714,
        -22.272,
        -328.647,
        8.95554,
        -202.916,
        235.091,
        -140.929,
        297.76,
        -36.8048,
        344.507
      ],
      "k_g": 62.9705,
      "loss": -271.326
    }
  },
  "3": {
    "full_model": {
      "best_combinational": {
        "accuracy": 0.818333,
        "indices": {
          "248": [
            7,
            1
          ]
        },
        "loss": -237.951
      },
      "final_elo_scores": [
        -75.4217,
        -405.044,
        -20.6423,
        165.725,
        -40.6581,
        118.347,
        335.855,
        219.025,
        -307.369,
        10.1636
      ],
      "k_c": 516.669,
      "k_g": 28.1557
    },
    "optimized_elo": {
      "accuracy": 0.806667,
      "final_elo_scores": [
        -117.315,
        -336.057,
        -25.834,
        175.452,
        -60.3752,
        137.727,
        332.088,
        186.313,
        -353.894,
        61.8735
      ],
      "k_g": 53.9777,
      "loss": -258.251
    }
  },
  "30": {
    "full_model": {
      "best_combinational": {
        "accuracy": 0.796667,
        "indices": {
          "124": [
            1,
            6
          ],
          "307": [
            6,
            0
          ]
        },
        "loss": -271.703
      },
      "final_elo_scores": [
        -196.371,
        -179.617,
        -344.248,
        -45.1866,
        190.956,
        51.5351,
        170.761,
        275.909,
        -70.6849,
        146.97
      ],
      "k_c": 278.131,
      "k_g": 34.9551
    },
    "optimized_elo": {
      "accuracy": 0.778333,
      "final_elo_scores": [
        -212.708,
        -199.446,
        -374.84,
        -53.6643,
        209.161,
        80.5513,
        174.682,
        278.362,
        -73.4947,
        171.426
      ],
      "k_g": 47.3003,
      "loss": -283.902
    }
  },
  "31": {
    "full_model": {
      "best_combinational": {
        "accuracy": 0.861667,
        "indices": {
          "218": [
            7,
            0
          ],
          "343": [
            4,
            6
          ],
          "379": [
            0,
            5
          ],
          "437": [
            7,
            0
          ]
        },
        "loss": -198.059
      },
      "final_elo_scores": [
        90.4671,
        -200.846,
        16.9858,
        -230.284,
        140.337,
        -419.405,
        -265.298,
        530.659,
        238.816,
        98.5773
      ],
      "k_c": 534.635,
      "k_g": 17.2057
    },
    "optimized_elo": {
      "accuracy": 0.816667,
      "final_elo_scores": [
        87.9156,
        -187.724,
        3.00718,
        -247.325,
        62.8799,
        -246.361,
        -335.683,
        444.353,
        246.509,
        172.433
      ],
      "k_g": 70.7917,
      "loss": -244.045
    }
  },
  "32": {
    "full_model": {
      "best_combinational": {
        "accuracy": 0.795,
        "indices": {
          "351": [
            1,
            4
          ]
        },
        "loss": -244.849
      },
      "final_elo_scores": [
        106.912,
        -35.8355,
        160.963,
        -130.25,
        -354.727,
        179.701,
        -230.41,
        383.709,
        -88.9268,
        8.91569
      ],
      "k_c": 465.944,
      "k_g": 43.7316
    },
    "optimized_elo": {
      "accuracy": 0.8,
      "final_elo_scores": [
        135.959,
        -87.8649,
        147.317,
        -116.255,
        -351.111,
        194.487,
        -245.085,
        422.066,
        -117.491,
        18.0426
      ],
      "k_g": 64.7543,
      "loss": -263.25
    }
  },
  "33": {
    "full_model": {
      "best_combinational": {
        "accuracy": 0.826667,
        "indices": {
          "238": [
            3,
            4
          ],
          "392": [
            9,
            5
          ],
          "402": [
            0,
            7
          ]
        },
        "loss": -244.189
      },
      "final_elo_scores": [
        123.781,
        -23.742,
        42.2472,
        328.803,
        -349.684,
        -331.594,
        52.8718,
        -291.519,
        122.794,
        326.006
      ],
      "k_c": 508.263,
      "k_g": 1.23117e-15
    },
    "optimized_elo": {
      "accuracy": 0.765,
      "final_elo_scores": [
        35.2725,
        -81.3991,
        43.0037,
        272.311,
        -385.455,
        -182.385,
        149.46,
        -241.168,
        119.204,
        271.118
      ],
      "k_g": 55.6975,
      "loss": -288.541
    }
  },
  "34": {
    "full_model": {
      "best_combinational": {
        "accuracy": 0.788333,
        "indices": {
          "115": [
            8,
            3
          ],
          "198": [
            1,
            7
          ],
          "327": [
            3,
            1
          ]
        },
        "loss": -269.429
      },
      "final_elo_scores": [
        -2.61043,
        -161.293,
        41.4631,
        197.538,
        -183.681,
        56.889,
        119.204,
        -282.919,
        171.375,
        44.0754
      ],
      "k_c": 419.06,
      "k_g": 7.70526e-91
    },
    "optimized_elo": {
      "accuracy": 0.753333,
      "final_elo_scores": [
        -67.1784,
        -139.468,
        -27.7485,
        139.032,
        -241.111,
        56.8214,
        237.562,
        -316.508,
        237.89,
        120.72
      ],
      "k_g": 49.9076,
      "loss": -303.729
    }
  },
  "35": {
    "full_model": {
      "best_combinational": {
        "accuracy": 0.853333,
        "indices": {
          "222": [
            6,
            5
          ],
          "360": [
            0,
            9
          ]
        },
        "loss": -235.923
      },
      "final_elo_scores": [
        82.3593,
        -92.7347,
        -186.935,
        260.716,
        -76.5479,
        69.946,
        303.695,
        -301.349,
        130.243,
        -189.37
      ],
      "k_c": 413.529,
      "k_g": 38.6018
    },
    "optimized_elo": {
      "accuracy": 0.828333,
      "final_elo_scores": [
        76.8175,
        -126.851,
        -204.0,
        334.242,
        -84.4329,
        65.1208,
        324.528,
        -369.774,
        177.795,
        -193.417
      ],
      "k_g": 71.5155,
      "loss": -261.562
    }
  },
  "36": {
    "full_model": {
      "best_combinational": {
        "accuracy": 0.871667,
        "indices": {
          "396": [
            3,
            5
          ]
        },
        "loss": -188.812
      },
      "final_elo_scores": [
        -37.5044,
        -153.543,
        -411.86,
        504.209,
        178.481,
        -512.049,
        -14.4947,
        87.7553,
        -51.9747,
        410.956
      ],
      "k_c": 725.673,
      "k_g": 38.4783
    },
    "optimized_elo": {
      "accuracy": 0.863333,
      "final_elo_scores": [
        -98.8561,
        -162.795,
        -436.341,
        364.317,
        192.548,
        -385.992,
        71.7095,
        38.7873,
        -54.0359,
        470.657
      ],
      "k_g": 82.3676,
      "loss": -210.149
    }
  },
  "37": {
    "full_model": {
      "best_combinational": {
        "accuracy": 0.808333,
        "indices": {
          "227": [
            9,
            4
          ],
          "352": [
            4,
            6
          ],
          "503": [
            8,
            1
          ]
        },
        "loss": -239.845
      },
      "final_elo_scores": [
        150.551,
        -307.031,
        -321.076,
        67.0101,
        105.037,
        -4.83034,
        -125.649,
        25.3609,
        159.398,
        251.258
      ],
      "k_c": 451.155,
      "k_g": 27.8579
    },
    "optimized_elo": {
      "accuracy": 0.783333,
      "final_elo_scores": [
        166.001,
        -270.775,
        -371.698,
        42.1413,
        138.065,
        6.16527,
        -145.931,
        24.3578,
        145.446,
        266.242
      ],
      "k_g": 63.5438,
      "loss": -276.689
    }
  },
  "38": {
    "full_model": {
      "best_combinational": {
        "accuracy": 0.813333,
        "indices": {
          "274": [
            7,
            6
          ],
          "380": [
            6,
            7
          ]
        },
        "loss": -233.212
      },
      "final_elo_scores": [
        -188.599,
        -69.2679,
        46.0887,
        92.0056,
        234.88,
        393.212,
        218.132,
        -489.821,
        -148.777,
        -87.9394
      ],
      "k_c": 822.621,
      "k_g": 43.6385
    },
    "optimized_elo": {
      "accuracy": 0.798333,
      "final_elo_scores": [
        -181.741,
        -76.7169,
        23.2998,
        46.132,
        220.02,
        421.05,
        197.219,
        -357.725,
        -169.425,
        -122.198
      ],
      "k_g": 69.572,
      "loss": -263.57
    }
  },
  "39": {
    "full_model": {
      "best_combinational": {
        "accuracy": 0.831667,
        "indices": {
          "211": [
            3,
            8
          ]
        },
        "loss": -237.372
      },
      "final_elo_scores": [
        -180.607,
        100.327,
        143.393,
        398.902,
        207.78,
        -141.701,
        -121.066,
        -46.0298,
        -370.808,
        9.81244
      ],
      "k_c": 559.439,
      "k_g": 20.555
    },
    "optimized_elo": {
      "accuracy": 0.82,
      "final_elo_scores": [
        -197.22,
        169.405,
        129.023,
        380.123,
        287.415,
        -168.042,
        -171.837,
        -28.956,
        -427.344,
        27.4071
      ],
      "k_g": 61.3883,
      "loss": -252.619
    }
  },
  "4": {
    "full_model": {
      "best_combinational": {
        "accuracy": 0.846667,
        "indices": {
          "176": [
            1,
            4
          ],
          "257": [
            7,
            8
          ],
          "299": [
            3,
            0
          ]
        },
        "loss": -218.433
      },
      "final_elo_scores": [
        -293.291,
        341.259,
        37.715,
        141.7,
        -245.746,
        208.389,
        -121.656,
        186.882,
        -324.987,
        69.7872
      ],
      "k_c": 443.915,
      "k_g": 19.8675
    },
    "optimized_elo": {
      "accuracy": 0.815,
      "final_elo_scores": [
        -271.996,
        332.183,
        71.2429,
        49.0319,
        -195.469,
        215.42,
        -146.144,
        230.226,
        -361.376,
        76.9319
      ],
      "k_g": 58.7804,
      "loss": -251.222
    }
  },
  "40": {
    "full_model": {
      "best_combinational": {
        "accuracy": 0.79,
        "indices": {
          "118": [
            8,
            7
          ],
          "273": [
            9,
            1
          ],
          "394": [
            1,
            8
          ]
        },
        "loss": -269.049
      },
      "final_elo_scores": [
        31.7001,
        172.782,
        -100.781,
        58.834,
        131.54,
        -142.517,
        178.248,
        -299.314,
        -257.423,
        226.9
      ],
      "k_c": 413.697,
      "k_g": 24.3143
    },
    "optimized_elo": {
      "accuracy": 0.76,
      "final_elo_scores": [
        12.6781,
        172.674,
        -67.5907,
        18.4048,
        144.707,
        -168.002,
        188.16,
        -289.993,
        -217.167,
        206.097
      ],
      "k_g": 49.4736,
      "loss": -302.434
    }
  },
  "41": {
    "full_model": {
      "best_combinational": {
        "accuracy": 0.84,
        "indices": {
          "193": [
            0,
            5
          ],
          "311": [
            4,
            6
          ]
        },
        "loss": -216.99
      },
      "final_elo_scores": [
        384.946,
        -128.118,
        179.317,
        181.354,
        153.67,
        -260.431,
        -297.773,
        -4.97648,
        -176.072,
        -31.9937
      ],
      "k_c": 447.335,
      "k_g": 34.6167
    },
    "optimized_elo": {
      "accuracy": 0.835,
      "final_elo_scores": [
        444.8,
        -161.277,
        229.643,
        184.349,
        181.59,
        -292.077,
        -328.142,
        7.11389,
        -180.47,
        -85.6077
      ],
      "k_g": 78.8472,
      "loss": -244.14
    }
  },
  "42": {
    "full_model": {
      "best_combinational": {
        "accuracy": 0.781667,
        "indices": {
          "65": [
            1,
            6
          ]
        },
        "loss": -283.259
      },
      "final_elo_scores": [
        241.825,
        15.9902,
        -199.744,
        -44.7651,
        244.077,
        23.6196,
        -173.729,
        -29.0805,
        3.70613,
        -81.8083
      ],
      "k_c": 271.001,
      "k_g": 23.5777
    },
    "optimized_elo": {
      "accuracy": 0.77,
      "final_elo_scores": [
        301.102,
        -35.7968,
        -260.562,
        0.157519,
        304.417,
        27.6706,
        -180.672,
        0.0144109,
        -39.0675,
        -117.162
      ],
      "k_g": 46.3946,
      "loss": -287.662
    }
  },
  "43": {
    "full_model": {
      "best_combinational": {
        "accuracy": 0.805,
        "indices": {
          "375": [
            8,
            3
          ]
        },
        "loss": -248.174
      },
      "final_elo_scores": [
        -18.8453,
        115.541,
        196.16,
        -310.194,
        -58.7868,
        164.648,
        -160.969,
        290.458,
        107.973,
        -325.989
      ],
      "k_c": 545.445,
      "k_g": 29.7401
    },
    "optimized_elo": {
      "accuracy": 0.793333,
      "final_elo_scores": [
        -25.5844,
        145.033,
        236.305,
        -291.934,
        -59.9245,
        192.888,
        -180.999,
        314.458,
        25.9087,
        -356.156
      ],
      "k_g": 55.886,
      "loss": -262.764
    }
  },
  "44": {
    "full_model": {
      "best_combinational": {
        "accuracy": 0.778333,
        "indices": {
          "166": [
            0,
            6
          ],
          "330": [
            6,
            3
          ]
        },
        "loss": -284.608
      },
      "final_elo_scores": [
        101.309,
        -161.822,
        93.9557,
        -315.352,
        -29.2045,
        -104.54,
        76.5118,
        290.611,
        -79.8209,
        128.355
      ],
      "k_c": 550.753,
      "k_g": 31.6878
    },
    "optimized_elo": {
      "accuracy": 0.751667,
      "final_elo_scores": [
        28.8332,
        -213.744,
        114.474,
        -281.834,
        -51.6968,
        -93.0845,
        79.7749,
        341.239,
        -101.795,
        177.837
      ],
      "k_g": 59.6834,
      "loss": -317.542
    }
  },
  "45": {
    "full_model": {
      "best_combinational": {
        "accuracy": 0.838333,
        "indices": {
          "80": [
            1,
            6
          ],
          "238": [
            6,
            1
          ]
        },
        "loss": -239.455
      },
      "final_elo_scores": [
        52.9394,
        -170.106,
        21.1515,
        212.371,
        137.756,
        -46.6505,
        340.275,
        -298.308,
        -195.601,
        -53.8404
      ],
      "k_c": 543.268,
      "k_g": 27.2248
    },
    "optimized_elo": {
      "accuracy": 0.798333,
      "final_elo_scores": [
        47.1492,
        -153.75,
        12.2981,
        217.579,
        183.103,
        -58.4069,
        374.607,
        -331.29,
        -224.787,
        -66.5024
      ],
      "k_g": 55.18,
      "loss": -273.31
    }
  },
  "46": {
    "full_model": {
      "best_combinational": {
        "accuracy": 0.828333,
        "indices": {
          "221": [
            8,
            4
          ],
          "358": [
            4,
            0
          ]
        },
        "loss": -238.937
      },
      "final_elo_scores": [
        -103.667,
        -361.43,
        -183.478,
        204.02,
        87.4587,
        166.047,
        7.40672,
        -160.987,
        346.897,
        -2.25411
      ],
      "k_c": 389.822,
      "k_g": 31.6457
    },
    "optimized_elo": {
      "accuracy": 0.806667,
      "final_elo_scores": [
        -56.0633,
        -413.633,
        -225.137,
        245.972,
        76.4802,
        168.541,
        27.684,
        -201.403,
        384.922,
        -7.32856
      ],
      "k_g": 65.0447,
      "loss": -256.779
    }
  },
  "47": {
    "full_model": {
      "best_combinational": {
        "accuracy": 0.838333,
        "indices": {
          "79": [
            1,
            2
          ],
          "397": [
            2,
            1
          ],
          "487": [
            1,
            0
          ]
        },
        "loss": -220.008
      },
      "final_elo_scores": [
        -467.246,
        74.2049,
        354.313,
        157.473,
        -122.534,
        236.314,
        -204.255,
        96.818,
        -242.792,
        117.643
      ],
      "k_c": 573.336,
      "k_g": 36.5297
    },
    "optimized_elo": {
      "accuracy": 0.805,
      "final_elo_scores": [
        -299.146,
        13.3124,
        307.17,
        115.647,
        -141.167,
        268.067,
        -132.698,
        83.5496,
        -327.22,
        112.449
      ],
      "k_g": 72.9146,
      "loss": -266.361
    }
  },
  "48": {
    "full_model": {
      "best_combinational": {
        "accuracy": 0.871667,
        "indices": {
          "92": [
            2,
            5
          ],
          "277": [
            0,
            3
          ]
        },
        "loss": -186.422
      },
      "final_elo_scores": [
        329.882,
        -31.0759,
        467.738,
        -386.049,
        -272.04,
        -425.722,
        18.0543,
        -183.549,
        430.901,
        51.815
      ],
      "k_c": 578.21,
      "k_g": 49.9548
    },
    "optimized_elo": {
      "accuracy": 0.845,
      "final_elo_scores": [
        361.007,
        19.8981,
        428.985,
        -392.737,
        -245.415,
        -456.306,
        4.89454,
        -192.923,
        411.899,
        60.7161
      ],
      "k_g": 85.7325,
      "loss": -212.8
    }
  },
  "49": {
    "full_model": {
      "best_combinational": {
        "accuracy": 0.843333,
        "indices": {
          "165": [
            7,
            8
          ]
        },
        "loss": -211.148
      },
      "final_elo_scores": [
        -252.177,
        146.442,
        199.935,
        -47.2561,
        -284.473,
        46.2597,
        115.31,
        384.49,
        -279.895,
        -28.6132
      ],
      "k_c": 472.238,
      "k_g": 34.4348
    },
    "optimized_elo": {
      "accuracy": 0.826667,
      "final_elo_scores": [
        -228.026,
        172.052,
        227.506,
        -51.1157,
        -341.944,
        55.2362,
        77.8396,
        394.619,
        -259.098,
        -47.0475
      ],
      "k_g": 60.5275,
      "loss": -226.209
    }
  },
  "5": {
    "full_model": {
      "best_combinational": {
        "accuracy": 0.826667,
        "indices": {
          "154": [
            3,
            5
          ],
          "277": [
            5,
            0
          ]
        },
        "loss": -243.732
      },
      "final_elo_scores": [
        -405.756,
        -276.047,
        37.3983,
        314.058,
        173.864,
        184.294,
        20.2207,
        178.996,
        -153.57,
        -73.4354
      ],
      "k_c": 483.398,
      "k_g": 38.3317
    },
    "optimized_elo": {
      "accuracy": 0.79,
      "final_elo_scores": [
        -390.601,
        -329.186,
        26.4849,
        348.289,
        172.823,
        180.695,
        55.8848,
        173.943,
        -173.952,
        -64.3395
      ],
      "k_g": 66.3263,
      "loss": -274.266
    }
  },
  "50": {
    "full_model": {
      "best_combinational": {
        "accuracy": 0.831667,
        "indices": {
          "238": [
            0,
            3
          ]
        },
        "loss": -242.454
      },
      "final_elo_scores": [
        199.03,
        62.6698,
        -281.267,
        -116.652,
        132.586,
        -56.0838,
        406.546,
        -231.952,
        184.735,
        -299.632
      ],
      "k_c": 582.355,
      "k_g": 48.1345
    },
    "optimized_elo": {
      "accuracy": 0.81,
      "final_elo_scores": [
        160.717,
        48.8673,
        -257.518,
        -94.4122,
        124.27,
        -51.0746,
        373.79,
        -201.663,
        165.309,
        -268.305
      ],
      "k_g": 48.4677,
      "loss": -254.435
    }
  },
  "51": {
    "full_model": {
      "best_combinational": {
        "accuracy": 0.865,
        "indices": {
          "176": [
            4,
            6
          ],
          "198": [
            8,
            1
          ],
          "308": [
            6,
            2
          ]
        },
        "loss": -216.604
      },
      "final_elo_scores": [
        33.5232,
        -395.67,
        -339.68,
        -98.1662,
        240.818,
        248.196,
        372.412,
        -129.612,
        8.12327,
        60.0036
      ],
      "k_c": 535.301,
      "k_g": 0.0
    },
    "optimized_elo": {
      "accuracy": 0.825,
      "final_elo_scores": [
        -65.1076,
        -312.732,
        -388.282,
        -26.6344,
        176.723,
        325.79,
        361.878,
        -179.393,
        -1.68359,
        109.432
      ],
      "k_g": 64.814,
      "loss": -247.322
    }
  },
  "52": {
    "full_model": {
      "best_combinational": {
        "accuracy": 0.818333,
        "indices": {
          "293": [
            1,
            2
          ]
        },
        "loss": -235.387
      },
      "final_elo_scores": [
        -175.859,
        127.06,
        -132.3,
        -271.488,
        214.99,
        -130.809,
        4.2361,
        339.452,
        139.567,
        -114.811
      ],
      "k_c": 431.255,
      "k_g": 29.3061
    },
    "optimized_elo": {
      "accuracy": 0.823333,
      "final_elo_scores": [
        -238.404,
        91.1789,
        -107.955,
        -313.636,
        214.32,
        -113.751,
        37.5959,
        373.323,
        164.295,
        -106.934
      ],
      "k_g": 49.5132,
      "loss": -249.466
    }
  },
  "53": {
    "full_model": {
      "best_combinational": {
        "accuracy": 0.803333,
        "indices": {
          "97": [
            4,
            7
          ],
          "297": [
            3,
            4
          ]
        },
        "loss": -251.655
      },
      "final_elo_scores": [
        -37.0635,
        -108.071,
        189.947,
        343.072,
        71.5102,
        75.8337,
        -287.555,
        -145.939,
        -86.627,
        -14.9927
      ],
      "k_c": 542.691,
      "k_g": 36.2719
    },
    "optimized_elo": {
      "accuracy": 0.778333,
      "final_elo_scores": [
        -45.2225,
        -146.667,
        244.445,
        394.211,
        123.464,
        47.1675,
        -339.024,
        -149.974,
        -88.9243,
        -39.4321
      ],
      "k_g": 69.5429,
      "loss": -287.659
    }
  },
  "54": {
    "full_model": {
      "best_combinational": {
        "accuracy": 0.84,
        "indices": {
          "163": [
            5,
            9
          ],
          "259": [
            2,
            1
          ]
        },
        "loss": -217.366
      },
      "final_elo_scores": [
        100.746,
        -376.949,
        317.057,
        92.3491,
        -26.1129,
        392.42,
        -91.2936,
        -90.5592,
        -0.166155,
        -317.48
      ],
      "k_c": 518.57,
      "k_g": 1.4314e-18
    },
    "optimized_elo": {
      "accuracy": 0.806667,
      "final_elo_scores": [
        65.5523,
        -265.147,
        259.347,
        115.466,
        -86.6922,
        420.788,
        -77.2242,
        -145.191,
        15.2892,
        -302.17
      ],
      "k_g": 64.7338,
      "loss": -268.249
    }
  },
  "55": {
    "full_model": {
      "best_combinational": {
        "accuracy": 0.833333,
        "indices": {
          "99": [
            3,
            8
          ],
          "510": [
            9,
            2
          ]
        },
        "loss": -230.479
      },
      "final_elo_scores": [
        -145.839,
        193.993,
        -112.992,
        327.445,
        -279.922,
        -96.0088,
        -18.5963,
        111.181,
        -338.401,
        359.192
      ],
      "k_c": 512.644,
      "k_g": 30.7051
    },
    "optimized_elo": {
      "accuracy": 0.813333,
      "final_elo_scores": [
        -144.946,
        206.999,
        -99.2694,
        344.097,
        -342.169,
        -104.928,
        -7.76139,
        111.163,
        -288.746,
        325.572
      ],
      "k_g": 57.0317,
      "loss": -248.134
    }
  },
  "56": {
    "full_model": {
      "best_combinational": {
        "accuracy": 0.813333,
        "indices": {
          "372": [
            5,
            1
          ],
          "392": [
            8,
            3
          ]
        },
        "loss": -257.74
      },
      "final_elo_scores": [
        -331.054,
        -132.084,
        205.412,
        -134.068,
        18.2455,
        187.733,
        -198.021,
        59.3076,
        263.605,
        61.0391
      ],
      "k_c": 326.452,
      "k_g": 28.0487
    },
    "optimized_elo": {
      "accuracy": 0.796667,
      "final_elo_scores": [
        -338.007,
        -139.917,
        187.413,
        -94.006,
        -0.535335,
        180.966,
        -206.437,
        68.4889,
        291.841,
        50.2534
      ],
      "k_g": 50.4882,
      "loss": -275.224
    }
  },
  "57": {
    "full_model": {
      "best_combinational": {
        "accuracy": 0.848333,
        "indices": {
          "72": [
            5,
            2
          ]
        },
        "loss": -209.445
      },
      "final_elo_scores": [
        370.919,
        -162.174,
        -412.699,
        -99.7656,
        -47.1118,
        260.271,
        199.51,
        -31.8833,
        -158.788,
        81.6871
      ],
      "k_c": 480.527,
      "k_g": 31.0677
    },
    "optimized_elo": {
      "accuracy": 0.84,
      "final_elo_scores": [
        413.872,
        -214.797,
        -452.349,
        -57.7722,
        -92.7276,
        270.061,
        267.759,
        -55.1441,
        -169.034,
        90.1029
      ],
      "k_g": 59.3202,
      "loss": -219.622
    }
  },
  "58": {
    "full_model": {
      "best_combinational": {
        "accuracy": 0.808333,
        "indices": {
          "202": [
            0,
            5
          ],
          "390": [
            5,
            0
          ]
        },
        "loss": -255.399
      },
      "final_elo_scores": [
        -267.239,
        205.572,
        -62.9441,
        161.966,
        13.4298,
        228.281,
        138.693,
        -182.34,
        -108.75,
        -126.615
      ],
      "k_c": 323.156,
      "k_g": 32.6751
    },
    "optimized_elo": {
      "accuracy": 0.8,
      "final_elo_scores": [
        -321.816,
        215.951,
        -46.1301,
        156.706,
        48.3768,
        272.02,
        147.174,
        -204.08,
        -122.298,
        -145.847
      ],
      "k_g": 55.292,
      "loss": -279.613
    }
  },
  "59": {
    "full_model": {
      "best_combinational": {
        "accuracy": 0.781667,
        "indices": {
          "208": [
            6,
            9
          ],
          "359": [
            5,
            8
          ]
        },
        "loss": -288.578
      },
      "final_elo_scores": [
        178.064,
        36.4302,
        -151.204,
        -173.709,
        154.998,
        240.758,
        192.329,
        4.87319,
        -320.632,
        -161.853
      ],
      "k_c": 379.525,
      "k_g": 36.0234
    },
    "optimized_elo": {
      "accuracy": 0.735,
      "final_elo_scores": [
        176.906,
        23.1024,
        -163.923,
        -209.708,
        173.621,
        266.142,
        178.708,
        -2.50472,
        -296.225,
        -146.062
      ],
      "k_g": 55.2024,
      "loss": -318.364
    }
  },
  "6": {
    "full_model": {
      "best_combinational": {
        "accuracy": 0.831667,
        "indices": {
          "247": [
            7,
            9
          ],
          "374": [
            2,
            3
          ],
          "395": [
            9,
            0
          ]
        },
        "loss": -236.414
      },
      "final_elo_scores": [
        -389.089,
        203.246,
        220.911,
        -249.85,
        -302.171,
        -40.1214,
        199.823,
        355.552,
        -154.793,
        156.59
      ],
      "k_c": 522.979,
      "k_g": 35.0234
    },
    "optimized_elo": {
      "accuracy": 0.798333,
      "final_elo_scores": [
        -354.705,
        191.953,
        198.46,
        -216.079,
        -267.817,
        -51.5245,
        195.596,
        324.209,
        -165.742,
        145.698
      ],
      "k_g": 66.3033,
      "loss": -272.858
    }
  },
  "60": {
    "full_model": {
      "best_combinational": {
        "accuracy": 0.828333,
        "indices": {
          "80": [
            5,
            3
          ],
          "249": [
            3,
            9
          ]
        },
        "loss": -239.703
      },
      "final_elo_scores": [
        200.604,
        -8.99834,
        -268.586,
        148.54,
        -25.2593,
        360.462,
        139.712,
        -173.565,
        -85.7759,
        -287.147
      ],
      "k_c": 397.407,
      "k_g": 34.0628
    },
    "optimized_elo": {
      "accuracy": 0.795,
      "final_elo_scores": [
        231.039,
        3.46184,
        -300.136,
        183.818,
        -2.85699,
        410.52,
        132.552,
        -210.779,
        -117.171,
        -330.465
      ],
      "k_g": 59.9016,
      "loss": -261.527
    }
  },
  "61": {
    "full_model": {
      "best_combinational": {
        "accuracy": 0.808333,
        "indices": {
          "397": [
            3,
            0
          ]
        },
        "loss": -276.939
      },
      "final_elo_scores": [
        -217.249,
        -122.113,
        175.306,
        235.524,
        -9.30075,
        -217.39,
        -45.8898,
        92.9544,
        -131.079,
        239.202
      ],
      "k_c": 449.698,
      "k_g": 35.7153
    },
    "optimized_elo": {
      "accuracy": 0.793333,
      "final_elo_scores": [
        -148.272,
        -118.06,
        169.361,
        223.839,
        4.62658,
        -226.791,
        -59.3991,
        76.905,
        -146.76,
        224.535
      ],
      "k_g": 46.3897,
      "loss": -297.2
    }
  },
  "62": {
    "full_model": {
      "best_combinational": {
        "accuracy": 0.796667,
        "indices": {
          "42": [
            4,
            0
          ],
          "241": [
            6,
            2
          ]
        },
        "loss": -258.159
      },
      "final_elo_scores": [
        -255.187,
        127.101,
        -356.115,
        -89.1589,
        270.386,
        -37.0365,
        242.741,
        -98.2975,
        68.4111,
        127.074
      ],
      "k_c": 469.112,
      "k_g": 26.5776
    },
    "optimized_elo": {
      "accuracy": 0.773333,
      "final_elo_scores": [
        -256.883,
        109.004,
        -305.033,
        -99.2186,
        281.935,
        -64.11,
        247.325,
        -132.327,
        82.3878,
        136.869
      ],
      "k_g": 46.4936,
      "loss": -281.444
    }
  },
  "63": {
    "full_model": {
      "best_combinational": {
        "accuracy": 0.83,
        "indices": {
          "212": [
            1,
            2
          ],
          "335": [
            3,
            7
          ],
          "514": [
            8,
            9
          ]
        },
        "loss": -235.34
      },
      "final_elo_scores": [
        -86.6369,
        393.915,
        -375.521,
        158.951,
        -55.0899,
        -128.091,
        88.5687,
        -227.065,
        398.455,
        -167.439
      ],
      "k_c": 475.484,
      "k_g": 34.6273
    },
    "optimized_elo": {
      "accuracy": 0.8,
      "final_elo_scores": [
        -68.2026,
        363.3,
        -398.372,
        94.5868,
        -2.99931,
        -131.886,
        133.532,
        -163.044,
        296.636,
        -123.512
      ],
      "k_g": 71.8681,
      "loss": -267.768
    }
  },
  "64": {
    "full_model": {
      "best_combinational": {
        "accuracy": 0.873333,
        "indices": {
          "250": [
            6,
            1
          ]
        },
        "loss": -206.538
      },
      "final_elo_scores": [
        92.5057,
        -423.503,
        -230.485,
        60.4664,
        -164.063,
        -103.882,
        457.953,
        323.663,
        -242.724,
        230.142
      ],
      "k_c": 643.264,
      "k_g": 45.8743
    },
    "optimized_elo": {
      "accuracy": 0.853333,
      "final_elo_scores": [
        94.0934,
        -415.155,
        -231.41,
        69.9138,
        -171.775,
        -106.066,
        381.53,
        317.942,
        -196.773,
        257.757
      ],
      "k_g": 73.597,
      "loss": -228.729
    }
  },
  "65": {
    "full_model": {
      "best_combinational": {
        "accuracy": 0.81,
        "indices": {
          "259": [
            4,
            3
          ]
        },
        "loss": -231.292
      },
      "final_elo_scores": [
        107.693,
        394.982,
        -178.506,
        -402.56,
        186.119,
        -191.609,
        -291.9,
        -31.906,
        205.211,
        202.402
      ],
      "k_c": 543.794,
      "k_g": 35.9384
    },
    "optimized_elo": {
      "accuracy": 0.815,
      "final_elo_scores": [
        120.949,
        425.639,
        -168.6,
        -413.361,
        170.845,
        -207.057,
        -298.685,
        -36.0481,
        216.062,
        190.227
      ],
      "k_g": 59.9573,
      "loss": -242.179
    }
  },
  "66": {
    "full_model": {
      "best_combinational": {
        "accuracy": 0.801667,
        "indices": {
          "78": [
            3,
            5
          ],
          "375": [
            5,
            8
          ]
        },
        "loss": -239.796
      },
      "final_elo_scores": [
        60.6389,
        -58.8505,
        -16.9188,
        397.675,
        59.4066,
        330.303,
        28.7071,
        -190.945,
        -383.188,
        -226.787
      ],
      "k_c": 428.065,
      "k_g": 39.2916
    },
    "optimized_elo": {
      "accuracy": 0.8,
      "final_elo_scores": [
        70.001,
        -53.2899,
        -2.74486,
        399.603,
        50.8282,
        346.193,
        64.9067,
        -234.893,
        -381.752,
        -258.821
      ],
      "k_g": 69.7799,
      "loss": -265.123
    }
  },
  "67": {
    "full_model": {
      "best_combinational": {
        "accuracy": 0.825,
        "indices": {
          "175": [
            9,
            7
          ],
          "321": [
            7,
            9
          ]
        },
        "loss": -253.254
      },
      "final_elo_scores": [
        -112.616,
        -70.5038,
        119.601,
        192.285,
        -176.754,
        31.4289,
        38.9301,
        309.576,
        -121.115,
        -211.14
      ],
      "k_c": 455.223,
      "k_g": 0.0
    },
    "optimized_elo": {
      "accuracy": 0.775,
      "final_elo_scores": [
        -79.7587,
        -111.955,
        45.3141,
        257.354,
        -236.33,
        104.707,
        91.9225,
        263.79,
        -151.983,
        -183.038
      ],
      "k_g": 45.2328,
      "loss": -285.89
    }
  },
  "68": {
    "full_model": {
      "best_combinational": {
        "accuracy": 0.851667,
        "indices": {
          "76": [
            6,
            4
          ],
          "192": [
            1,
            0
          ]
        },
        "loss": -224.736
      },
      "final_elo_scores": [
        -290.348,
        372.869,
        0.614128,
        277.65,
        -296.963,
        -190.278,
        178.672,
        -20.6526,
        -107.1,
        75.5435
      ],
      "k_c": 509.098,
      "k_g": 27.438
    },
    "optimized_elo": {
      "accuracy": 0.831667,
      "final_elo_scores": [
        -247.983,
        372.15,
        22.8605,
        310.135,
        -315.568,
        -232.602,
        170.326,
        -7.31656,
        -132.197,
        60.2064
      ],
      "k_g": 53.1906,
      "loss": -245.174
    }
  },
  "69": {
    "full_model": {
      "best_combinational": {
        "accuracy": 0.81,
        "indices": {
          "211": [
            5,
            9
          ],
          "368": [
            9,
            5
          ]
        },
        "loss": -248.789
      },
      "final_elo_scores": [
        -323.706,
        159.814,
        23.2708,
        222.447,
        -197.201,
        -453.087,
        55.9432,
        -78.1624,
        282.35,
        308.356
      ],
      "k_c": 665.703,
      "k_g": 39.64
    },
    "optimized_elo": {
      "accuracy": 0.786667,
      "final_elo_scores": [
        -337.082,
        158.979,
        -14.0212,
        226.899,
        -133.945,
        -351.037,
        -6.86652,
        -52.8957,
        251.814,
        258.162
      ],
      "k_g": 70.1398,
      "loss": -273.439
    }
  },
  "7": {
    "full_model": {
      "best_combinational": {
        "accuracy": 0.816667,
        "indices": {
          "95": [
            0,
            5
          ],
          "281": [
            9,
            7
          ]
        },
        "loss": -228.094
      },
      "final_elo_scores": [
        429.927,
        63.5346,
        -139.725,
        156.004,
        -117.101,
        -337.591,
        110.418,
        -182.62,
        -272.09,
        289.271
      ],
      "k_c": 438.83,
      "k_g": 39.9498
    },
    "optimized_elo": {
      "accuracy": 0.796667,
      "final_elo_scores": [
        476.713,
        80.6521,
        -121.049,
        156.939,
        -104.778,
        -367.276,
        93.5958,
        -170.261,
        -331.904,
        287.39
      ],
      "k_g": 67.8017,
      "loss": -249.863
    }
  },
  "70": {
    "full_model": {
      "best_combinational": {
        "accuracy": 0.856667,
        "indices": {
          "162": [
            3,
            7
          ],
          "331": [
            1,
            2
          ]
        },
        "loss": -203.882
      },
      "final_elo_scores": [
        272.022,
        203.691,
        -342.033,
        96.7693,
        19.4525,
        137.864,
        368.701,
        -396.604,
        -197.097,
        -162.759
      ],
      "k_c": 481.71,
      "k_g": 41.4097
    },
    "optimized_elo": {
      "accuracy": 0.838333,
      "final_elo_scores": [
        300.546,
        187.635,
        -314.813,
        89.4415,
        -10.1478,
        203.764,
        361.708,
        -409.464,
        -258.927,
        -149.735
      ],
      "k_g": 77.2562,
      "loss": -229.008
    }
  },
  "71": {
    "full_model": {
      "best_combinational": {
        "accuracy": 0.831667,
        "indices": {
          "332": [
            8,
            2
          ]
        },
        "loss": -244.621
      },
      "final_elo_scores": [
        -357.295,
        -46.9779,
        -261.418,
        -225.287,
        -58.6028,
        286.894,
        348.142,
        88.245,
        145.456,
        80.8839
      ],
      "k_c": 459.456,
      "k_g": 47.9339
    },
    "optimized_elo": {
      "accuracy": 0.82,
      "final_elo_scores": [
        -356.024,
        -49.8381,
        -233.713,
        -243.398,
        -56.9459,
        295.85,
        351.083,
        87.5261,
        142.155,
        63.3439
      ],
      "k_g": 57.5181,
      "loss": -260.328
    }
  },
  "72": {
    "full_model": {
      "best_combinational": {
        "accuracy": 0.848333,
        "indices": {
          "173": [
            6,
            3
          ]
        },
        "loss": -217.143
      },
      "final_elo_scores": [
        308.836,
        -120.467,
        -401.04,
        -275.442,
        87.5178,
        70.0445,
        488.822,
        116.976,
        -254.883,
        -20.4016
      ],
      "k_c": 601.771,
      "k_g": 52.7962
    },
    "optimized_elo": {
      "accuracy": 0.82,
      "final_elo_scores": [
        297.647,
        -135.365,
        -401.959,
        -257.928,
        101.022,
        67.2394,
        471.068,
        121.34,
        -239.367,
        -23.7358
      ],
      "k_g": 65.3032,
      "loss": -235.745
    }
  },
  "73": {
    "full_model": {
      "best_combinational": {
        "accuracy": 0.826667,
        "indices": {
          "343": [
            8,
            6
          ],
          "430": [
            0,
            1
          ]
        },
        "loss": -257.893
      },
      "final_elo_scores": [
        238.156,
        -223.149,
        -100.439,
        15.7532,
        -122.115,
        -224.45,
        -166.581,
        164.426,
        218.596,
        199.944
      ],
      "k_c": 462.605,
      "k_g": 14.8158
    },
    "optimized_elo": {
      "accuracy": 0.79,
      "final_elo_scores": [
        180.965,
        -146.559,
        -91.4859,
        33.4092,
        -141.904,
        -323.724,
        -131.187,
        205.41,
        206.566,
        208.651
      ],
      "k_g": 54.5356,
      "loss": -276.206
    }
  },
  "74": {
    "full_model": {
      "best_combinational": {
        "accuracy": 0.785,
        "indices": {
          "180": [
            3,
            8
          ],
          "190": [
            5,
            1
          ],
          "373": [
            8,
            3
          ]
        },
        "loss": -280.001
      },
      "final_elo_scores": [
        -7.63134,
        -260.577,
        -30.7866,
        -103.896,
        84.2472,
        158.189,
        66.4783,
        -59.7585,
        246.996,
        -93.2036
      ],
      "k_c": 394.49,
      "k_g": 14.0348
    },
    "optimized_elo": {
      "accuracy": 0.74,
      "final_elo_scores": [
        54.9252,
        -321.259,
        -35.4683,
        -100.966,
        122.945,
        207.462,
        14.0858,
        -62.8076,
        291.095,
        -169.953
      ],
      "k_g": 49.99,
      "loss": -318.336
    }
  },
  "75": {
    "full_model": {
      "best_combinational": {
        "accuracy": 0.853333,
        "indices": {
          "315": [
            6,
            3
          ]
        },
        "loss": -225.794
      },
      "final_elo_scores": [
        180.091,
        104.514,
        -148.387,
        -298.208,
        -156.776,
        236.257,
        355.416,
        -25.4565,
        177.808,
        -425.263
      ],
      "k_c": 545.719,
      "k_g": 52.6822
    },
    "optimized_elo": {
      "accuracy": 0.833333,
      "final_elo_scores": [
        193.44,
        64.8539,
        -151.878,
        -314.481,
        -178.866,
        293.23,
        389.314,
        -25.5434,
        195.586,
        -465.655
      ],
      "k_g": 83.678,
      "loss": -240.106
    }
  },
  "76": {
    "full_model": {
      "best_combinational": {
        "accuracy": 0.816667,
        "indices": {
          "46": [
            8,
            5
          ],
          "135": [
            0,
            8
          ],
          "369": [
            8,
            0
          ]
        },
        "loss": -250.18
      },
      "final_elo_scores": [
        -135.59,
        193.957,
        120.029,
        -59.3982,
        -77.9503,
        -317.829,
        65.412,
        -5.32348,
        143.461,
        73.1517
      ],
      "k_c": 605.338,
      "k_g": 20.6472
    },
    "optimized_elo": {
      "accuracy": 0.763333,
      "final_elo_scores": [
        -185.857,
        249.639,
        159.694,
        -55.4502,
        -123.828,
        -354.854,
        25.8092,
        37.3426,
        141.832,
        105.614
      ],
      "k_g": 63.1335,
      "loss": -296.573
    }
  },
  "77": {
    "full_model": {
      "best_combinational": {
        "accuracy": 0.831667,
        "indices": {
          "295": [
            8,
            9
          ]
        },
        "loss": -216.235
      },
      "final_elo_scores": [
        -323.996,
        -229.033,
        168.67,
        327.34,
        71.7433,
        -39.477,
        291.822,
        -108.747,
        291.056,
        -449.4
      ],
      "k_c": 691.077,
      "k_g": 50.0503
    },
    "optimized_elo": {
      "accuracy": 0.811667,
      "final_elo_scores": [
        -363.391,
        -258.117,
        206.181,
        338.947,
        51.4626,
        -58.5892,
        329.239,
        -128.097,
        249.519,
        -367.174
      ],
      "k_g": 78.6031,
      "loss": -242.932
    }
  },
  "78": {
    "full_model": {
      "best_combinational": {
        "accuracy": 0.833333,
        "indices": {
          "103": [
            2,
            9
          ],
          "251": [
            9,
            4
          ]
        },
        "loss": -237.986
      },
      "final_elo_scores": [
        243.921,
        -18.5969,
        363.599,
        -264.718,
        -229.822,
        -31.7026,
        -194.721,
        86.0091,
        -143.058,
        189.108
      ],
      "k_c": 486.347,
      "k_g": 39.0115
    },
    "optimized_elo": {
      "accuracy": 0.813333,
      "final_elo_scores": [
        301.689,
        -7.87778,
        395.617,
        -306.201,
        -208.363,
        -80.051,
        -205.695,
        99.9333,
        -203.665,
        214.64
      ],
      "k_g": 74.3806,
      "loss": -267.498
    }
  },
  "79": {
    "full_model": {
      "best_combinational": {
        "accuracy": 0.801667,
        "indices": {
          "394": [
            3,
            6
          ]
        },
        "loss": -253.089
      },
      "final_elo_scores": [
        -73.2395,
        235.198,
        -298.531,
        96.3399,
        344.582,
        -72.3389,
        -22.689,
        93.3269,
        -17.802,
        -284.813
      ],
      "k_c": 407.897,
      "k_g": 45.1593
    },
    "optimized_elo": {
      "accuracy": 0.793333,
      "final_elo_scores": [
        -69.7213,
        245.236,
        -363.467,
        79.7841,
        416.679,
        -75.8886,
        8.81257,
        108.899,
        -25.1775,
        -325.145
      ],
      "k_g": 70.4325,
      "loss": -259.483
    }
  },
  "8": {
    "full_model": {
      "best_combinational": {
        "accuracy": 0.843333,
        "indices": {
          "61": [
            3,
            8
          ],
          "351": [
            8,
            2
          ]
        },
        "loss": -223.528
      },
      "final_elo_scores": [
        -19.4742,
        -122.651,
        -413.284,
        414.881,
        -113.828,
        -304.891,
        117.04,
        71.3675,
        303.226,
        67.6273
      ],
      "k_c": 511.249,
      "k_g": 31.4578
    },
    "optimized_elo": {
      "accuracy": 0.806667,
      "final_elo_scores": [
        -4.4191,
        -137.642,
        -416.013,
        452.898,
        -146.07,
        -330.842,
        177.45,
        65.2163,
        267.207,
        72.2567
      ],
      "k_g": 71.9937,
      "loss": -258.124
    }
  },
  "80": {
    "full_model": {
      "best_combinational": {
        "accuracy": 0.835,
        "indices": {
          "141": [
            7,
            3
          ],
          "256": [
            6,
            5
          ]
        },
        "loss": -203.123
      },
      "final_elo_scores": [
        -247.671,
        -30.703,
        -163.918,
        -558.791,
        188.836,
        -377.137,
        559.05,
        375.395,
        236.501,
        18.396
      ],
      "k_c": 670.16,
      "k_g": 38.9406
    },
    "optimized_elo": {
      "accuracy": 0.821667,
      "final_elo_scores": [
        -237.138,
        22.3324,
        -155.64,
        -481.514,
        146.084,
        -389.349,
        483.098,
        265.427,
        283.272,
        63.4236
      ],
      "k_g": 79.6829,
      "loss": -233.912
    }
  },
  "81": {
    "full_model": {
      "best_combinational": {
        "accuracy": 0.805,
        "indices": {
          "70": [
            4,
            6
          ],
          "297": [
            6,
            4
          ]
        },
        "loss": -249.157
      },
      "final_elo_scores": [
        -187.593,
        -34.7001,
        83.2854,
        228.909,
        -179.643,
        -305.349,
        76.798,
        -92.2327,
        236.374,
        174.121
      ],
      "k_c": 410.677,
      "k_g": 31.3397
    },
    "optimized_elo": {
      "accuracy": 0.795,
      "final_elo_scores": [
        -198.512,
        -38.8169,
        79.8027,
        275.769,
        -203.307,
        -309.915,
        74.789,
        -115.557,
        259.548,
        176.169
      ],
      "k_g": 50.3508,
      "loss": -276.714
    }
  },
  "82": {
    "full_model": {
      "best_combinational": {
        "accuracy": 0.796667,
        "indices": {
          "327": [
            6,
            0
          ]
        },
        "loss": -244.987
      },
      "final_elo_scores": [
        -533.414,
        -126.707,
        -61.2436,
        -59.577,
        -71.6618,
        217.832,
        395.984,
        232.707,
        -77.7136,
        83.731
      ],
      "k_c": 661.023,
      "k_g": 19.088
    },
    "optimized_elo": {
      "accuracy": 0.776667,
      "final_elo_scores": [
        -376.157,
        -119.62,
        -102.819,
        -28.7823,
        -156.184,
        234.262,
        345.534,
        247.188,
        -135.714,
        92.2382
      ],
      "k_g": 56.0333,
      "loss": -273.144
    }
  },
  "83": {
    "full_model": {
      "best_combinational": {
        "accuracy": 0.815,
        "indices": {
          "146": [
            4,
            9
          ]
        },
        "loss": -247.276
      },
      "final_elo_scores": [
        77.938,
        39.6256,
        -133.096,
        -149.936,
        385.605,
        139.476,
        176.227,
        -38.7099,
        -53.3374,
        -443.895
      ],
      "k_c": 386.271,
      "k_g": 53.8867
    },
    "optimized_elo": {
      "accuracy": 0.806667,
      "final_elo_scores": [
        78.1975,
        35.3139,
        -129.507,
        -151.171,
        380.198,
        142.698,
        173.767,
        -43.1327,
        -56.0393,
        -430.426
      ],
      "k_g": 57.0332,
      "loss": -262.714
    }
  },
  "84": {
    "full_model": {
      "best_combinational": {
        "accuracy": 0.818333,
        "indices": {
          "183": [
            2,
            3
          ]
        },
        "loss": -244.612
      },
      "final_elo_scores": [
        24.528,
        -221.945,
        -67.9138,
        -364.422,
        258.787,
        133.809,
        53.7108,
        -106.268,
        73.189,
        216.464
      ],
      "k_c": 428.27,
      "k_g": 38.628
    },
    "optimized_elo": {
      "accuracy": 0.803333,
      "final_elo_scores": [
        38.6268,
        -237.055,
        -73.2193,
        -396.779,
        299.517,
        139.562,
        58.0483,
        -114.061,
        69.281,
        216.046
      ],
      "k_g": 53.7751,
      "loss": -256.713
    }
  },
  "85": {
    "full_model": {
      "best_combinational": {
        "accuracy": 0.838333,
        "indices": {
          "156": [
            7,
            1
          ],
          "282": [
            2,
            3
          ]
        },
        "loss": -199.708
      },
      "final_elo_scores": [
        -12.5677,
        -503.29,
        323.413,
        -154.9,
        148.421,
        -413.079,
        -275.297,
        642.733,
        336.585,
        -92.0286
      ],
      "k_c": 786.849,
      "k_g": 52.1896
    },
    "optimized_elo": {
      "accuracy": 0.815,
      "final_elo_scores": [
        -26.9859,
        -381.014,
        268.476,
        -111.804,
        163.16,
        -384.025,
        -215.653,
        495.395,
        319.599,
        -127.169
      ],
      "k_g": 72.4284,
      "loss": -219.838
    }
  },
  "86": {
    "full_model": {
      "best_combinational": {
        "accuracy": 0.845,
        "indices": {
          "63": [
            1,
            8
          ],
          "246": [
            7,
            1
          ]
        },
        "loss": -212.772
      },
      "final_elo_scores": [
        323.941,
        -116.071,
        1.23387,
        -248.695,
        70.0582,
        -27.3413,
        84.4178,
        380.036,
        -393.908,
        -73.6557
      ],
      "k_c": 555.651,
      "k_g": 24.1247
    },
    "optimized_elo": {
      "accuracy": 0.818333,
      "final_elo_scores": [
        300.198,
        -67.7696,
        55.481,
        -266.331,
        86.5024,
        -47.3802,
        57.7002,
        343.022,
        -388.749,
        -72.6778
      ],
      "k_g": 54.2849,
      "loss": -250.907
    }
  },
  "87": {
    "full_model": {
      "best_combinational": {
        "accuracy": 0.785,
        "indices": {
          "255": [
            6,
            4
          ]
        },
        "loss": -253.968
      },
      "final_elo_scores": [
        127.913,
        190.622,
        212.058,
        -67.2298,
        -233.81,
        -171.27,
        416.548,
        -41.0706,
        -48.5837,
        -385.232
      ],
      "k_c": 521.253,
      "k_g": 40.4773
    },
    "optimized_elo": {
      "accuracy": 0.766667,
      "final_elo_scores": [
        133.219,
        198.833,
        233.89,
        -74.8287,
        -225.478,
        -190.733,
        396.099,
        -9.80609,
        -54.1615,
        -407.091
      ],
      "k_g": 56.9825,
      "loss": -271.518
    }
  },
  "88": {
    "full_model": {
      "best_combinational": {
        "accuracy": 0.825,
        "indices": {
          "205": [
            9,
            2
          ]
        },
        "loss": -233.178
      },
      "final_elo_scores": [
        -424.288,
        -190.569,
        -259.018,
        30.758,
        -22.8006,
        -67.7588,
        234.517,
        116.764,
        288.413,
        293.949
      ],
      "k_c": 318.344,
      "k_g": 50.2903
    },
    "optimized_elo": {
      "accuracy": 0.821667,
      "final_elo_scores": [
        -473.607,
        -222.315,
        -275.083,
        18.1217,
        -13.4808,
        -67.1769,
        251.603,
        125.184,
        320.503,
        336.244
      ],
      "k_g": 72.2896,
      "loss": -242.123
    }
  },
  "89": {
    "full_model": {
      "best_combinational": {
        "accuracy": 0.801667,
        "indices": {
          "196": [
            9,
            5
          ]
        },
        "loss": -258.787
      },
      "final_elo_scores": [
        -287.649,
        126.384,
        99.4851,
        -251.945,
        335.484,
        -229.561,
        88.2211,
        32.318,
        -145.915,
        233.158
      ],
      "k_c": 471.536,
      "k_g": 45.6611
    },
    "optimized_elo": {
      "accuracy": 0.8,
      "final_elo_scores": [
        -307.58,
        142.035,
        103.973,
        -269.65,
        351.112,
        -225.704,
        87.1898,
        26.2263,
        -141.498,
        233.898
      ],
      "k_g": 59.2307,
      "loss": -272.69
    }
  },
  "9": {
    "full_model": {
      "best_combinational": {
        "accuracy": 0.808333,
        "indices": {
          "141": [
            4,
            6
          ],
          "249": [
            9,
            4
          ],
          "346": [
            4,
            2
          ]
        },
        "loss": -252.566
      },
      "final_elo_scores": [
        -5.49574,
        -201.561,
        36.0459,
        -213.895,
        255.999,
        120.418,
        -205.784,
        -115.353,
        68.4559,
        261.201
      ],
      "k_c": 388.119,
      "k_g": 27.9472
    },
    "optimized_elo": {
      "accuracy": 0.77,
      "final_elo_scores": [
        7.20699,
        -221.497,
        79.5093,
        -257.943,
        273.645,
        152.054,
        -225.879,
        -135.345,
        83.6996,
        244.54
      ],
      "k_g": 53.522,
      "loss": -277.717
    }
  },
  "90": {
    "full_model": {
      "best_combinational": {
        "accuracy": 0.845,
        "indices": {
          "74": [
            5,
            7
          ],
          "162": [
            4,
            5
          ]
        },
        "loss": -198.94
      },
      "final_elo_scores": [
        387.965,
        46.1223,
        58.1038,
        189.516,
        300.947,
        -157.91,
        -26.7644,
        -505.62,
        -36.3387,
        -256.01
      ],
      "k_c": 566.407,
      "k_g": 36.8335
    },
    "optimized_elo": {
      "accuracy": 0.811667,
      "final_elo_scores": [
        426.822,
        60.5228,
        50.0722,
        183.941,
        296.237,
        -195.177,
        -17.0705,
        -461.603,
        -63.9327,
        -279.796
      ],
      "k_g": 68.8529,
      "loss": -232.629
    }
  },
  "91": {
    "full_model": {
      "best_combinational": {
        "accuracy": 0.858333,
        "indices": {
          "96": [
            0,
            8
          ],
          "391": [
            2,
            9
          ]
        },
        "loss": -205.435
      },
      "final_elo_scores": [
        411.948,
        -181.836,
        133.603,
        3.91005,
        -117.85,
        177.998,
        -192.006,
        207.562,
        -89.1992,
        -354.174
      ],
      "k_c": 561.115,
      "k_g": 52.262
    },
    "optimized_elo": {
      "accuracy": 0.838333,
      "final_elo_scores": [
        415.709,
        -173.109,
        97.8681,
        6.97779,
        -96.2066,
        194.44,
        -244.484,
        259.19,
        -75.6267,
        -384.801
      ],
      "k_g": 97.4153,
      "loss": -241.649
    }
  },
  "92": {
    "full_model": {
      "best_combinational": {
        "accuracy": 0.863333,
        "indices": {
          "75": [
            7,
            0
          ],
          "341": [
            0,
            4
          ]
        },
        "loss": -214.981
      },
      "final_elo_scores": [
        249.827,
        -65.4157,
        244.045,
        -360.756,
        -255.263,
        -2.01084,
        133.423,
        224.849,
        -32.9207,
        -135.742
      ],
      "k_c": 495.335,
      "k_g": 39.0859
    },
    "optimized_elo": {
      "accuracy": 0.831667,
      "final_elo_scores": [
        236.521,
        -62.6339,
        283.566,
        -418.683,
        -283.094,
        -47.8878,
        168.148,
        261.123,
        -44.6864,
        -92.395
      ],
      "k_g": 73.6888,
      "loss": -243.922
    }
  },
  "93": {
    "full_model": {
      "best_combinational": {
        "accuracy": 0.841667,
        "indices": {
          "145": [
            4,
            8
          ],
          "275": [
            1,
            5
          ]
        },
        "loss": -219.591
      },
      "final_elo_scores": [
        -215.512,
        288.849,
        95.0587,
        74.0331,
        426.896,
        -371.625,
        252.416,
        -83.116,
        -355.533,
        -111.527
      ],
      "k_c": 556.27,
      "k_g": 31.1995
    },
    "optimized_elo": {
      "accuracy": 0.81,
      "final_elo_scores": [
        -238.203,
        268.636,
        105.113,
        41.3461,
        453.955,
        -350.821,
        285.315,
        -120.325,
        -356.346,
        -88.7229
      ],
      "k_g": 64.4502,
      "loss": -240.52
    }
  },
  "94": {
    "full_model": {
      "best_combinational": {
        "accuracy": 0.823333,
        "indices": {
          "139": [
            7,
            3
          ],
          "379": [
            0,
            8
          ]
        },
        "loss": -232.958
      },
      "final_elo_scores": [
        286.03,
        -224.257,
        127.724,
        -94.9672,
        219.259,
        50.842,
        -42.9102,
        168.46,
        -296.41,
        -193.833
      ],
      "k_c": 417.275,
      "k_g": 23.7087
    },
    "optimized_elo": {
      "accuracy": 0.806667,
      "final_elo_scores": [
        369.984,
        -335.567,
        195.238,
        -97.1407,
        245.882,
        54.3465,
        -16.9102,
        116.062,
        -322.425,
        -209.511
      ],
      "k_g": 66.0781,
      "loss": -254.329
    }
  },
  "95": {
    "full_model": {
      "best_combinational": {
        "accuracy": 0.886667,
        "indices": {
          "150": [
            9,
            0
          ],
          "306": [
            4,
            0
          ]
        },
        "loss": -170.65
      },
      "final_elo_scores": [
        -613.967,
        -132.3,
        103.512,
        -17.3392,
        24.4885,
        80.3044,
        -365.968,
        359.334,
        169.911,
        392.041
      ],
      "k_c": 541.373,
      "k_g": 48.1718
    },
    "optimized_elo": {
      "accuracy": 0.866667,
      "final_elo_scores": [
        -504.929,
        -156.191,
        52.5402,
        -9.04873,
        19.1363,
        69.2141,
        -432.125,
        416.701,
        146.683,
        398.035
      ],
      "k_g": 83.2031,
      "loss": -193.94
    }
  },
  "96": {
    "full_model": {
      "best_combinational": {
        "accuracy": 0.8,
        "indices": {
          "147": [
            2,
            4
          ],
          "360": [
            4,
            2
          ]
        },
        "loss": -256.429
      },
      "final_elo_scores": [
        160.084,
        -11.4913,
        -243.174,
        60.2324,
        99.0816,
        120.005,
        -151.828,
        -241.231,
        -155.695,
        363.99
      ],
      "k_c": 440.574,
      "k_g": 40.5659
    },
    "optimized_elo": {
      "accuracy": 0.776667,
      "final_elo_scores": [
        192.13,
        -28.9492,
        -254.803,
        66.914,
        112.887,
        122.411,
        -172.978,
        -301.459,
        -137.405,
        401.227
      ],
      "k_g": 64.2722,
      "loss": -282.504
    }
  },
  "97": {
    "full_model": {
      "best_combinational": {
        "accuracy": 0.811667,
        "indices": {
          "218": [
            1,
            0
          ],
          "378": [
            9,
            6
          ]
        },
        "loss": -237.053
      },
      "final_elo_scores": [
        -349.622,
        45.9642,
        410.005,
        -291.651,
        175.584,
        -35.6725,
        -324.045,
        -60.6725,
        112.099,
        318.002
      ],
      "k_c": 545.166,
      "k_g": 41.6377
    },
    "optimized_elo": {
      "accuracy": 0.793333,
      "final_elo_scores": [
        -289.477,
        22.3424,
        415.566,
        -272.854,
        165.673,
        -28.9412,
        -349.384,
        -44.7701,
        103.082,
        278.721
      ],
      "k_g": 69.5659,
      "loss": -272.431
    }
  },
  "98": {
    "full_model": {
      "best_combinational": {
        "accuracy": 0.786667,
        "indices": {
          "196": [
            2,
            6
          ],
          "318": [
            9,
            5
          ],
          "332": [
            6,
            2
          ]
        },
        "loss": -281.904
      },
      "final_elo_scores": [
        -119.306,
        10.9857,
        -143.74,
        12.2173,
        211.246,
        -244.904,
        144.513,
        41.7112,
        -9.03526,
        95.9565
      ],
      "k_c": 388.066,
      "k_g": 7.377e-320
    },
    "optimized_elo": {
      "accuracy": 0.73,
      "final_elo_scores": [
        -21.877,
        -10.2657,
        -207.787,
        1.39567,
        256.314,
        -215.542,
        198.38,
        -8.33275,
        -58.2398,
        65.923
      ],
      "k_g": 38.5152,
      "loss": -324.321
    }
  },
  "99": {
    "full_model": {
      "best_combinational": {
        "accuracy": 0.841667,
        "indices": {
          "205": [
            0,
            6
          ],
          "371": [
            5,
            7
          ]
        },
        "loss": -214.262
      },
      "final_elo_scores": [
        264.99,
        74.5013,
        239.662,
        275.234,
        -238.149,
        -46.3594,
        -373.639,
        17.6936,
        -45.5158,
        -168.25
      ],
      "k_c": 495.188,
      "k_g": 44.5382
    },
    "optimized_elo": {
      "accuracy": 0.821667,
      "final_elo_scores": [
        259.413,
        72.2808,
        241.42,
        312.848,
        -279.079,
        -60.7347,
        -382.534,
        46.4492,
        -46.4315,
        -163.463
      ],
      "k_g": 68.8187,
      "loss": -243.85
    }
  }
}